[
    {
        "kind": "youtube#video",
        "etag": "oOvIyX0Svk7dhMxCGuF28q8v7cQ",
        "id": "DbfPkC4NfJ0",
        "snippet": {
            "publishedAt": "2021-11-10T05:20:03Z",
            "channelId": "UC0AwKOBh0HM3rVUgrSSCHqw",
            "title": "Amber Heard Breaks Silence On Being SENTENCED To 4 Years In Prison On Case Against Johnny Depp",
            "description": "Amber Heard Breaks Silence On Being SENTENCED To 4 Years In Prison!\n\n\ud83d\udcf2 For More Content like this, be sure to Subscribe to our channel! \n\n\u2705Thanks For Watching: Amber Heard Breaks Silence On Being SENTENCED To 4 Years In Prison!\n\n\u2b50Check out our Playlist: Top Celebrity Life Drama And Gossip!\n\nWe post Top Trending and Viral Celebrity Life and Celebrity Drama. We create a daily dose of The Most Amazing Top 10 and also Top 5 type of videos that trend. We aim to create satisfying videos about Celebrities, Rich Popstars, Stars, Models, Rappers in Hip Hop Content. We also provide our audience with the latest celebrity news about famous people and the secret celebrity gossip that is going on in the lives of these famous celebrities!\n\nIn this video we uncover, once and for all, what really happened between the Johnny Depp and Amber Heard Divorce and Lawsuit Drama. Did Amber Heard abuse Johnny Depp or was it the other way around? Who was the one in the right? Did Amber Heard really Lie? We also cover Amber Heard speaking on being sentenced to 4 years in prison! Watch this video until the very end to see how Amber heard admits to abusing Johnny Depp.\n\n\n\ud83d\udcbbFor Business Inquiries, Collaborations or Promotions, contact us\n\n\nTags:\n\njohnny depp amber heard, amber heard sentence,amber heard prison,amber heard, johnny depp,amber heard johnny depp,amber heard interview,amber heard apology,amber heard admits,amber heard abuse,amber heard lied,Amber Heard Admits to Abusing Johnny Depp,amber heard lawsuit,johnny depp amber heard court,johnny depp court,amber heard court,johnny depp sues amber heard,johnny depp wins,amber heard loses,amber heard in court,amber heard johnny depp audio,viral,trending,justin bieber,lana del rey,kylie jenner,kanye west,jimmy fallon,kim kardashian,kardashians,selena gomez,ariana grande,zendaya,taylor swift,Amber Heard,The Weeknd,Addison rae,jack harlow,celebrities,celebs,celeb,celebrity,popstar,rich,stars,models,shorts,rappers,hip hop,celebrity news,famous people,celebrity gossip, gossip,news celebrity,famous celebrities,popular celebrities,top celebrities,popular,top celebrities",
            "thumbnails": {
                "default": {
                    "url": "https://i.ytimg.com/vi/DbfPkC4NfJ0/default.jpg",
                    "width": 120,
                    "height": 90
                },
                "medium": {
                    "url": "https://i.ytimg.com/vi/DbfPkC4NfJ0/mqdefault.jpg",
                    "width": 320,
                    "height": 180
                },
                "high": {
                    "url": "https://i.ytimg.com/vi/DbfPkC4NfJ0/hqdefault.jpg",
                    "width": 480,
                    "height": 360
                },
                "standard": {
                    "url": "https://i.ytimg.com/vi/DbfPkC4NfJ0/sddefault.jpg",
                    "width": 640,
                    "height": 480
                },
                "maxres": {
                    "url": "https://i.ytimg.com/vi/DbfPkC4NfJ0/maxresdefault.jpg",
                    "width": 1280,
                    "height": 720
                }
            },
            "channelTitle": "Celebrity Gossip",
            "tags": [
                "viral video",
                "trend",
                "celebrities",
                "celebrity",
                "rap",
                "celebrity news",
                "famous people",
                "celebrity gossip",
                "gossip",
                "famous celebrities",
                "popular celebrities",
                "popular",
                "top celebrities",
                "viral",
                "celebrity drama",
                "kardashians",
                "famous people gossip",
                "news celebrity",
                "johnny depp amber heard",
                "johnny depp",
                "amber heard johnny depp",
                "johnny depp amber heard court",
                "johnny depp sues amber heard",
                "amber heard sentence",
                "amber heard sentenced to 4 years",
                "amber heard prison",
                "amber heard sentenced",
                "amber heard"
            ],
            "categoryId": "22",
            "liveBroadcastContent": "none",
            "defaultLanguage": "en-US",
            "localized": {
                "title": "Amber Heard Breaks Silence On Being SENTENCED To 4 Years In Prison On Case Against Johnny Depp",
                "description": "Amber Heard Breaks Silence On Being SENTENCED To 4 Years In Prison!\n\n\ud83d\udcf2 For More Content like this, be sure to Subscribe to our channel! \n\n\u2705Thanks For Watching: Amber Heard Breaks Silence On Being SENTENCED To 4 Years In Prison!\n\n\u2b50Check out our Playlist: Top Celebrity Life Drama And Gossip!\n\nWe post Top Trending and Viral Celebrity Life and Celebrity Drama. We create a daily dose of The Most Amazing Top 10 and also Top 5 type of videos that trend. We aim to create satisfying videos about Celebrities, Rich Popstars, Stars, Models, Rappers in Hip Hop Content. We also provide our audience with the latest celebrity news about famous people and the secret celebrity gossip that is going on in the lives of these famous celebrities!\n\nIn this video we uncover, once and for all, what really happened between the Johnny Depp and Amber Heard Divorce and Lawsuit Drama. Did Amber Heard abuse Johnny Depp or was it the other way around? Who was the one in the right? Did Amber Heard really Lie? We also cover Amber Heard speaking on being sentenced to 4 years in prison! Watch this video until the very end to see how Amber heard admits to abusing Johnny Depp.\n\n\n\ud83d\udcbbFor Business Inquiries, Collaborations or Promotions, contact us\n\n\nTags:\n\njohnny depp amber heard, amber heard sentence,amber heard prison,amber heard, johnny depp,amber heard johnny depp,amber heard interview,amber heard apology,amber heard admits,amber heard abuse,amber heard lied,Amber Heard Admits to Abusing Johnny Depp,amber heard lawsuit,johnny depp amber heard court,johnny depp court,amber heard court,johnny depp sues amber heard,johnny depp wins,amber heard loses,amber heard in court,amber heard johnny depp audio,viral,trending,justin bieber,lana del rey,kylie jenner,kanye west,jimmy fallon,kim kardashian,kardashians,selena gomez,ariana grande,zendaya,taylor swift,Amber Heard,The Weeknd,Addison rae,jack harlow,celebrities,celebs,celeb,celebrity,popstar,rich,stars,models,shorts,rappers,hip hop,celebrity news,famous people,celebrity gossip, gossip,news celebrity,famous celebrities,popular celebrities,top celebrities,popular,top celebrities"
            },
            "defaultAudioLanguage": "en-US"
        },
        "contentDetails": {
            "duration": "PT9M9S",
            "dimension": "2d",
            "definition": "hd",
            "caption": "false",
            "licensedContent": false,
            "contentRating": {},
            "projection": "rectangular"
        },
        "status": {
            "uploadStatus": "processed",
            "privacyStatus": "public",
            "license": "youtube",
            "embeddable": true,
            "publicStatsViewable": true,
            "madeForKids": false
        },
        "statistics": {
            "viewCount": "1112",
            "likeCount": "36",
            "dislikeCount": "2",
            "favoriteCount": "0",
            "commentCount": "12"
        }
    }
]