[
    {
        "kind": "youtube#video",
        "etag": "ZhxK6tt7kBum_I44Yqgpyytwflg",
        "id": "o84odsce90o",
        "snippet": {
            "publishedAt": "2020-07-15T17:02:16Z",
            "channelId": "UC5y8hRV8JsZbDiQ2dxdwysw",
            "title": "Johnny Depp Explains Amber Heard is Crazy (With Body Language Meaning)",
            "description": "Female domestic abuse\nJohnny Depp Explains Amber Heard is Crazy",
            "thumbnails": {
                "default": {
                    "url": "https://i.ytimg.com/vi/o84odsce90o/default.jpg",
                    "width": 120,
                    "height": 90
                },
                "medium": {
                    "url": "https://i.ytimg.com/vi/o84odsce90o/mqdefault.jpg",
                    "width": 320,
                    "height": 180
                },
                "high": {
                    "url": "https://i.ytimg.com/vi/o84odsce90o/hqdefault.jpg",
                    "width": 480,
                    "height": 360
                },
                "standard": {
                    "url": "https://i.ytimg.com/vi/o84odsce90o/sddefault.jpg",
                    "width": 640,
                    "height": 480
                },
                "maxres": {
                    "url": "https://i.ytimg.com/vi/o84odsce90o/maxresdefault.jpg",
                    "width": 1280,
                    "height": 720
                }
            },
            "channelTitle": "Basil Gentleman",
            "categoryId": "24",
            "liveBroadcastContent": "none",
            "localized": {
                "title": "Johnny Depp Explains Amber Heard is Crazy (With Body Language Meaning)",
                "description": "Female domestic abuse\nJohnny Depp Explains Amber Heard is Crazy"
            }
        },
        "contentDetails": {
            "duration": "PT1M22S",
            "dimension": "2d",
            "definition": "hd",
            "caption": "false",
            "licensedContent": false,
            "contentRating": {},
            "projection": "rectangular"
        },
        "status": {
            "uploadStatus": "processed",
            "privacyStatus": "public",
            "license": "youtube",
            "embeddable": true,
            "publicStatsViewable": false,
            "madeForKids": false
        },
        "statistics": {
            "viewCount": "3664",
            "likeCount": "84",
            "favoriteCount": "0",
            "commentCount": "3"
        }
    }
]