[
    {
        "kind": "youtube#video",
        "etag": "sPrA2GYUSLrvPB-npMHJRMUHl1Q",
        "id": "0Hsg3SoGkL4",
        "snippet": {
            "publishedAt": "2021-11-29T20:15:00Z",
            "channelId": "UCZlnshKh_exh1WBP9P-yPdQ",
            "title": "A Total War Saga: Troy - Odysseus Mythos - 14",
            "description": "A Total War Saga: Troy - Odysseus Mythos - 14\n\nOdysseus is back and his party draws ever closer to the Griffin  whilst in the mean time diplomacy continues to be...challenging. Don't miss the Epic action in the latest episode.\n\n#TotalWar \n#MYTHOS \n#TROY\n\nA Total War Saga: Troy on the steam store:\nhttps://store.steampowered.com/app/1099410/A_Total_War_Saga_TROY/\n\nJoin the HeirofCarthage Discord!\nhttps://discord.gg/EWyCGGa\n\nLike my new Channel branding? Check out Havoc\n https://twitter.com/hforhavoc\n\nSupport me on Patreon!\nhttps://www.patreon.com/HeirofCarthage\n\nFollow me on Twitter!\nhttps://twitter.com/HeirTweets",
            "thumbnails": {
                "default": {
                    "url": "https://i.ytimg.com/vi/0Hsg3SoGkL4/default.jpg",
                    "width": 120,
                    "height": 90
                },
                "medium": {
                    "url": "https://i.ytimg.com/vi/0Hsg3SoGkL4/mqdefault.jpg",
                    "width": 320,
                    "height": 180
                },
                "high": {
                    "url": "https://i.ytimg.com/vi/0Hsg3SoGkL4/hqdefault.jpg",
                    "width": 480,
                    "height": 360
                },
                "standard": {
                    "url": "https://i.ytimg.com/vi/0Hsg3SoGkL4/sddefault.jpg",
                    "width": 640,
                    "height": 480
                },
                "maxres": {
                    "url": "https://i.ytimg.com/vi/0Hsg3SoGkL4/maxresdefault.jpg",
                    "width": 1280,
                    "height": 720
                }
            },
            "channelTitle": "HeirofCarthage",
            "tags": [
                "Online",
                "Battle",
                "Campaign",
                "Vortex",
                "HeirofCarthage",
                "Heir",
                "of",
                "Carthage",
                "Commentary",
                "Tips",
                "Strategy",
                "Advice",
                "Walkthrough",
                "A Total War Saga: Troy",
                "#TotalWar",
                "#MYTHOS",
                "#TROY",
                "Mythos",
                "A Total War Saga: Troy - Odysseus Mythos - 14"
            ],
            "categoryId": "20",
            "liveBroadcastContent": "none",
            "localized": {
                "title": "A Total War Saga: Troy - Odysseus Mythos - 14",
                "description": "A Total War Saga: Troy - Odysseus Mythos - 14\n\nOdysseus is back and his party draws ever closer to the Griffin  whilst in the mean time diplomacy continues to be...challenging. Don't miss the Epic action in the latest episode.\n\n#TotalWar \n#MYTHOS \n#TROY\n\nA Total War Saga: Troy on the steam store:\nhttps://store.steampowered.com/app/1099410/A_Total_War_Saga_TROY/\n\nJoin the HeirofCarthage Discord!\nhttps://discord.gg/EWyCGGa\n\nLike my new Channel branding? Check out Havoc\n https://twitter.com/hforhavoc\n\nSupport me on Patreon!\nhttps://www.patreon.com/HeirofCarthage\n\nFollow me on Twitter!\nhttps://twitter.com/HeirTweets"
            }
        },
        "contentDetails": {
            "duration": "PT1H11S",
            "dimension": "2d",
            "definition": "hd",
            "caption": "false",
            "licensedContent": true,
            "contentRating": {},
            "projection": "rectangular"
        },
        "status": {
            "uploadStatus": "processed",
            "privacyStatus": "public",
            "license": "youtube",
            "embeddable": true,
            "publicStatsViewable": true,
            "madeForKids": false
        },
        "statistics": {
            "viewCount": "1505",
            "likeCount": "92",
            "dislikeCount": "2",
            "favoriteCount": "0",
            "commentCount": "31"
        }
    }
]