[
    {
        "kind": "youtube#channel",
        "etag": "E9LVYd5scgrpLI57YbOtYqyeZSE",
        "id": "UCmIaztc4t_eMF3AqjkgF3HA",
        "snippet": {
            "title": "Monnster zone",
            "description": "Best movies hindi full HD  hollywood plus bollywood plus animation movies\n  Best HD trailer in 1080p  in Hindi and English  Official Trailer 4K and Hollywood films and Bollywood films trailers rapidly  also animated films trailers  new trailer 2020 new trailer 2021 new trailer 2022 new trailer2023 new movies trailers  new games trailer trailer world noew games 2021 trailer.   Whatsapp Status ",
            "publishedAt": "2018-07-03T17:44:42Z",
            "thumbnails": {
                "default": {
                    "url": "https://yt3.ggpht.com/6X9_ljJYF3i90Ln1uCq4kDuj3rKsOkwYB83HgW58F7ucJKApcge6tCyCn85d8VUY9mBb9Fumgw=s88-c-k-c0x00ffffff-no-rj",
                    "width": 88,
                    "height": 88
                },
                "medium": {
                    "url": "https://yt3.ggpht.com/6X9_ljJYF3i90Ln1uCq4kDuj3rKsOkwYB83HgW58F7ucJKApcge6tCyCn85d8VUY9mBb9Fumgw=s240-c-k-c0x00ffffff-no-rj",
                    "width": 240,
                    "height": 240
                },
                "high": {
                    "url": "https://yt3.ggpht.com/6X9_ljJYF3i90Ln1uCq4kDuj3rKsOkwYB83HgW58F7ucJKApcge6tCyCn85d8VUY9mBb9Fumgw=s800-c-k-c0x00ffffff-no-rj",
                    "width": 800,
                    "height": 800
                }
            },
            "localized": {
                "title": "Monnster zone",
                "description": "Best movies hindi full HD  hollywood plus bollywood plus animation movies\n  Best HD trailer in 1080p  in Hindi and English  Official Trailer 4K and Hollywood films and Bollywood films trailers rapidly  also animated films trailers  new trailer 2020 new trailer 2021 new trailer 2022 new trailer2023 new movies trailers  new games trailer trailer world noew games 2021 trailer.   Whatsapp Status "
            },
            "country": "PK"
        },
        "contentDetails": {
            "relatedPlaylists": {
                "likes": "",
                "uploads": "UUmIaztc4t_eMF3AqjkgF3HA"
            }
        },
        "statistics": {
            "viewCount": "2575",
            "subscriberCount": "58",
            "hiddenSubscriberCount": false,
            "videoCount": "420"
        },
        "topicDetails": {
            "topicIds": [
                "/m/02vxn",
                "/m/0f2f9",
                "/m/02jjt"
            ],
            "topicCategories": [
                "https://en.wikipedia.org/wiki/Film",
                "https://en.wikipedia.org/wiki/Television_program",
                "https://en.wikipedia.org/wiki/Entertainment"
            ]
        },
        "status": {
            "privacyStatus": "public",
            "isLinked": true,
            "longUploadsStatus": "longUploadsUnspecified",
            "madeForKids": false
        },
        "brandingSettings": {
            "channel": {
                "title": "Monnster zone",
                "description": "Best movies hindi full HD  hollywood plus bollywood plus animation movies\n  Best HD trailer in 1080p  in Hindi and English  Official Trailer 4K and Hollywood films and Bollywood films trailers rapidly  also animated films trailers  new trailer 2020 new trailer 2021 new trailer 2022 new trailer2023 new movies trailers  new games trailer trailer world noew games 2021 trailer.   Whatsapp Status ",
                "keywords": "\"Pakistan zindabad\" \"6d movie\" 6Dmovie 6dmovie 6movies sixmovies trailers \"new trailers\" \"hd trailers\" \"monster zone\" \"Monnter zone\" \"Monnter zone\" \"Monnter zone\" \"Monnter zone\" \"monnter zone\" \"monter zone\" \"monnster zone\" \"Monnster zone\" \"Monnster zone\" \"XRed Zone\" xredzone \"xred zone\" \"Xred Zone\" \"ZOne REDX\" \"zone xred\" \"ZONE XRED\" \"new movies trailer 2021\" \"new movies trailers 2022\" \"new games trailer\" \"new games 2021 trailer\"",
                "unsubscribedTrailer": "F8XIfMVtJuY",
                "country": "PK"
            }
        },
        "contentOwnerDetails": {}
    }
]