[
    {
        "kind": "youtube#video",
        "etag": "2Jli9bjMZo7jKqJtbu3h9cKIPf0",
        "id": "GI7xdmDadII",
        "snippet": {
            "publishedAt": "2020-07-24T16:41:41Z",
            "channelId": "UCMAwi5fm2yOSEeKd_Qv0Z2Q",
            "title": "Amber Heard CRUSHED in Court as PROOF she BEAT HER SISTER is EXPOSED!",
            "description": "COMIC: https://www.indiegogo.com/projects/the-case-of-the-littlest-umbrella#/\r\n\r\nTip Jar: https://www.paypal.com/cgi-bin/webscr?cmd=_s-xclick&hosted_button_id=2AAZU385W88GE    Tip Jar\r\n\r\nPatreon: https://www.patreon.com/thatumbrellaguy Patreon\r\n#johnnydepp #amberheard #thesun",
            "thumbnails": {
                "default": {
                    "url": "https://i.ytimg.com/vi/GI7xdmDadII/default.jpg",
                    "width": 120,
                    "height": 90
                },
                "medium": {
                    "url": "https://i.ytimg.com/vi/GI7xdmDadII/mqdefault.jpg",
                    "width": 320,
                    "height": 180
                },
                "high": {
                    "url": "https://i.ytimg.com/vi/GI7xdmDadII/hqdefault.jpg",
                    "width": 480,
                    "height": 360
                },
                "standard": {
                    "url": "https://i.ytimg.com/vi/GI7xdmDadII/sddefault.jpg",
                    "width": 640,
                    "height": 480
                },
                "maxres": {
                    "url": "https://i.ytimg.com/vi/GI7xdmDadII/maxresdefault.jpg",
                    "width": 1280,
                    "height": 720
                }
            },
            "channelTitle": "ThatUmbrellaGuy",
            "tags": [
                "amber heard",
                "amber heard attacked sister",
                "amber heard body language",
                "amber heard booed",
                "amber heard deposition",
                "amber heard james corden",
                "amber heard johnny depp",
                "amber heard sister",
                "amber heard whitney",
                "depp trial today",
                "heard depp case",
                "heard depp sun",
                "heard depp trial",
                "johnny depp",
                "johnny depp interview",
                "johnny depp news",
                "johnny depp trial",
                "that umbrella guy johnny depp",
                "thatumbrellaguy amber heard",
                "thatumbrellaguy johnny depp",
                "the sun trial",
                "umbrella guy"
            ],
            "categoryId": "24",
            "liveBroadcastContent": "none",
            "localized": {
                "title": "Amber Heard CRUSHED in Court as PROOF she BEAT HER SISTER is EXPOSED!",
                "description": "COMIC: https://www.indiegogo.com/projects/the-case-of-the-littlest-umbrella#/\r\n\r\nTip Jar: https://www.paypal.com/cgi-bin/webscr?cmd=_s-xclick&hosted_button_id=2AAZU385W88GE    Tip Jar\r\n\r\nPatreon: https://www.patreon.com/thatumbrellaguy Patreon\r\n#johnnydepp #amberheard #thesun"
            },
            "defaultAudioLanguage": "en"
        },
        "contentDetails": {
            "duration": "PT11M50S",
            "dimension": "2d",
            "definition": "hd",
            "caption": "false",
            "licensedContent": true,
            "contentRating": {},
            "projection": "rectangular"
        },
        "status": {
            "uploadStatus": "processed",
            "privacyStatus": "public",
            "license": "youtube",
            "embeddable": true,
            "publicStatsViewable": true,
            "madeForKids": false
        },
        "statistics": {
            "viewCount": "31320",
            "likeCount": "2186",
            "favoriteCount": "0",
            "commentCount": "234"
        }
    }
]