[
    {
        "kind": "youtube#video",
        "etag": "XCpvOugdmejAr16t6K8oAFEPFWA",
        "id": "Dlcnso-aQ_o",
        "snippet": {
            "publishedAt": "2012-01-15T01:28:23Z",
            "channelId": "UC4ODiXgBehmS3i_Lu_GUt2A",
            "title": "MYTHS: A Video No \"Straight\" You Tube Male Wants To See.",
            "description": "UPDATE! Amber Heard is quite the Douche Bag for opportunistically fucking Johnny Depp just because she thinks that it wil advance her career. Kim Kardashian is not the only \"Ho\" in Hollywood.\n\nPay Attention! I Don't Care If You Rate This Video Poorly Because You Know It's TRUE!\n\nLesbians are NOT fat and ugly [well most of us aren't]. We don't need a good f--k by some loser guy who can't satisfy a woman anyway and we haven't been hurt by you.\n\nThe truth is: Males are just not important to a lesbian's life. I know rejection hurts but put on your \"big boy\" pants and deal with it. I am TIRED of Indulging male insecurity.",
            "thumbnails": {
                "default": {
                    "url": "https://i.ytimg.com/vi/Dlcnso-aQ_o/default.jpg",
                    "width": 120,
                    "height": 90
                },
                "medium": {
                    "url": "https://i.ytimg.com/vi/Dlcnso-aQ_o/mqdefault.jpg",
                    "width": 320,
                    "height": 180
                },
                "high": {
                    "url": "https://i.ytimg.com/vi/Dlcnso-aQ_o/hqdefault.jpg",
                    "width": 480,
                    "height": 360
                }
            },
            "channelTitle": "X-MISMA-X",
            "tags": [
                "lesbians",
                "lesbian relationships"
            ],
            "categoryId": "24",
            "liveBroadcastContent": "none",
            "localized": {
                "title": "MYTHS: A Video No \"Straight\" You Tube Male Wants To See.",
                "description": "UPDATE! Amber Heard is quite the Douche Bag for opportunistically fucking Johnny Depp just because she thinks that it wil advance her career. Kim Kardashian is not the only \"Ho\" in Hollywood.\n\nPay Attention! I Don't Care If You Rate This Video Poorly Because You Know It's TRUE!\n\nLesbians are NOT fat and ugly [well most of us aren't]. We don't need a good f--k by some loser guy who can't satisfy a woman anyway and we haven't been hurt by you.\n\nThe truth is: Males are just not important to a lesbian's life. I know rejection hurts but put on your \"big boy\" pants and deal with it. I am TIRED of Indulging male insecurity."
            }
        },
        "contentDetails": {
            "duration": "PT3M23S",
            "dimension": "2d",
            "definition": "sd",
            "caption": "false",
            "licensedContent": false,
            "contentRating": {},
            "projection": "rectangular"
        },
        "status": {
            "uploadStatus": "processed",
            "privacyStatus": "public",
            "license": "youtube",
            "embeddable": true,
            "publicStatsViewable": false,
            "madeForKids": false
        },
        "statistics": {
            "viewCount": "845",
            "favoriteCount": "0"
        }
    }
]