[
    {
        "kind": "youtube#video",
        "etag": "iEpPg5cZmS5arLiXfQIRKfwNdgA",
        "id": "D5neEzKMClA",
        "snippet": {
            "publishedAt": "2016-10-21T17:24:05Z",
            "channelId": "UCm9uAvqwZjgvSgAHU57Q3wQ",
            "title": "Amber Case - Calm Technology",
            "description": "How is our relationship with computers changing the way we think and act? Ask Amber Case, a user experience designer and cyborg anthropologist who studies the interactions between man and machine.\n\nAmber\u2019s thoughts on our connection to our new external brains have fascinated audiences at SXSW, and her TED talk, \u201cWe are all Cyborgs now\u201d, has been viewed over a million times. Case is the author of An Illustrated Dictionary of Cyborg Anthropology and Calm Technology, and the founder of CyborgCamp, an unconference on the future of humans and computers. One of National Geographic\u2019s Emerging Explorers, she is the co-founder and former CEO of Geoloqi, a location-based startup that was acquired by Esri in 2012.\n\nSubscribe to her channel: http://youtube.com/caseorganic\n\n---\nTHINKING DIGITAL\nLatest news: https://thinkingdigital.co.uk\nFollow: http://twitter.com/thinkingdigital\nLike: http://facebook.com/thinkingdigital",
            "thumbnails": {
                "default": {
                    "url": "https://i.ytimg.com/vi/D5neEzKMClA/default.jpg",
                    "width": 120,
                    "height": 90
                },
                "medium": {
                    "url": "https://i.ytimg.com/vi/D5neEzKMClA/mqdefault.jpg",
                    "width": 320,
                    "height": 180
                },
                "high": {
                    "url": "https://i.ytimg.com/vi/D5neEzKMClA/hqdefault.jpg",
                    "width": 480,
                    "height": 360
                },
                "standard": {
                    "url": "https://i.ytimg.com/vi/D5neEzKMClA/sddefault.jpg",
                    "width": 640,
                    "height": 480
                },
                "maxres": {
                    "url": "https://i.ytimg.com/vi/D5neEzKMClA/maxresdefault.jpg",
                    "width": 1280,
                    "height": 720
                }
            },
            "channelTitle": "Thinking Digital Conference",
            "tags": [
                "Thinking Digital",
                "TDCMCR",
                "Thinking Digital Manchester",
                "Amber Case",
                "Cyborgs",
                "Calm Tech",
                "CyborgCamp",
                "Manchester",
                "Technology",
                "amber case ted",
                "amber case ted talk",
                "amber case calm technology",
                "Calm Technology Amber Case",
                "amber case calm ted",
                "We are all Cyborgs now ted",
                "amber case We are all Cyborgs now",
                "Amber Case - Calm Technology",
                "amber case anthropologist"
            ],
            "categoryId": "28",
            "liveBroadcastContent": "none",
            "localized": {
                "title": "Amber Case - Calm Technology",
                "description": "How is our relationship with computers changing the way we think and act? Ask Amber Case, a user experience designer and cyborg anthropologist who studies the interactions between man and machine.\n\nAmber\u2019s thoughts on our connection to our new external brains have fascinated audiences at SXSW, and her TED talk, \u201cWe are all Cyborgs now\u201d, has been viewed over a million times. Case is the author of An Illustrated Dictionary of Cyborg Anthropology and Calm Technology, and the founder of CyborgCamp, an unconference on the future of humans and computers. One of National Geographic\u2019s Emerging Explorers, she is the co-founder and former CEO of Geoloqi, a location-based startup that was acquired by Esri in 2012.\n\nSubscribe to her channel: http://youtube.com/caseorganic\n\n---\nTHINKING DIGITAL\nLatest news: https://thinkingdigital.co.uk\nFollow: http://twitter.com/thinkingdigital\nLike: http://facebook.com/thinkingdigital"
            },
            "defaultAudioLanguage": "en-GB"
        },
        "contentDetails": {
            "duration": "PT27M40S",
            "dimension": "2d",
            "definition": "hd",
            "caption": "true",
            "licensedContent": true,
            "contentRating": {},
            "projection": "rectangular"
        },
        "status": {
            "uploadStatus": "processed",
            "privacyStatus": "public",
            "license": "youtube",
            "embeddable": true,
            "publicStatsViewable": true,
            "madeForKids": false
        },
        "statistics": {
            "viewCount": "16552",
            "likeCount": "272",
            "favoriteCount": "0",
            "commentCount": "3"
        }
    }
]