[
    {
        "kind": "youtube#video",
        "etag": "c-jo-7hNtaASrVCYmE_DOZESR_Y",
        "id": "0tefaP7Gj2A",
        "snippet": {
            "publishedAt": "2013-10-20T23:49:56Z",
            "channelId": "UC-NW-rrURx2QEyRVL3Exw6w",
            "title": "\u25b6 Amber Heard hot kissing scene lip seen video   YouTube",
            "description": "",
            "thumbnails": {
                "default": {
                    "url": "https://i.ytimg.com/vi/0tefaP7Gj2A/default.jpg",
                    "width": 120,
                    "height": 90
                },
                "medium": {
                    "url": "https://i.ytimg.com/vi/0tefaP7Gj2A/mqdefault.jpg",
                    "width": 320,
                    "height": 180
                },
                "high": {
                    "url": "https://i.ytimg.com/vi/0tefaP7Gj2A/hqdefault.jpg",
                    "width": 480,
                    "height": 360
                }
            },
            "channelTitle": "salman khan",
            "categoryId": "22",
            "liveBroadcastContent": "none",
            "localized": {
                "title": "\u25b6 Amber Heard hot kissing scene lip seen video   YouTube",
                "description": ""
            }
        },
        "contentDetails": {
            "duration": "PT2M28S",
            "dimension": "2d",
            "definition": "sd",
            "caption": "false",
            "licensedContent": false,
            "contentRating": {
                "ytRating": "ytAgeRestricted"
            },
            "projection": "rectangular"
        },
        "status": {
            "uploadStatus": "processed",
            "privacyStatus": "public",
            "license": "youtube",
            "embeddable": true,
            "publicStatsViewable": true,
            "madeForKids": false
        },
        "statistics": {
            "viewCount": "30881",
            "likeCount": "39",
            "favoriteCount": "0",
            "commentCount": "3"
        }
    }
]